PicFetch/__init__.py
PicFetch/dependencies.py
PicFetch/path.py
PicFetch/read.py
PicFetch/show.py
PicFetch/upload.py
PicFetch-0.1.dist-info/LICENSE
PicFetch-0.1.dist-info/METADATA
PicFetch-0.1.dist-info/WHEEL
PicFetch-0.1.dist-info/top_level.txt
PicFetch-0.1.dist-info/RECORD
