Metadata-Version: 2.1
Name: PicFetch
Version: 0.1
Summary: Receive images from the internet or local. Save them anywhere in the memory. Display a single image or multiple images. 
Home-page: UNKNOWN
Author: MahsaSanaei
Author-email: mahsasanaei.n@gmail.com
License: UNKNOWN
Platform: UNKNOWN
License-File: LICENSE
Requires-Dist: Pillow (==10.0.0)
Requires-Dist: Pygments (==2.16.1)
Requires-Dist: asttokens (==2.2.1)
Requires-Dist: backcall (==0.2.0)
Requires-Dist: certifi (==2023.7.22)
Requires-Dist: charset-normalizer (==3.2.0)
Requires-Dist: comm (==0.1.4)
Requires-Dist: contourpy (==1.1.0)
Requires-Dist: cycler (==0.11.0)
Requires-Dist: debugpy (==1.6.7.post1)
Requires-Dist: decorator (==5.1.1)
Requires-Dist: executing (==1.2.0)
Requires-Dist: fonttools (==4.42.1)
Requires-Dist: idna (==3.4)
Requires-Dist: ipykernel (==6.25.1)
Requires-Dist: ipython (==8.14.0)
Requires-Dist: jedi (==0.19.0)
Requires-Dist: jupyter-client (==8.3.0)
Requires-Dist: jupyter-core (==5.3.1)
Requires-Dist: kiwisolver (==1.4.5)
Requires-Dist: matplotlib-inline (==0.1.6)
Requires-Dist: matplotlib (==3.7.2)
Requires-Dist: nest-asyncio (==1.5.7)
Requires-Dist: numpy (==1.25.2)
Requires-Dist: opencv-python (==4.8.0.76)
Requires-Dist: packaging (==23.1)
Requires-Dist: parso (==0.8.3)
Requires-Dist: pexpect (==4.8.0)
Requires-Dist: pickleshare (==0.7.5)
Requires-Dist: platformdirs (==3.10.0)
Requires-Dist: prompt-toolkit (==3.0.39)
Requires-Dist: psutil (==5.9.5)
Requires-Dist: ptyprocess (==0.7.0)
Requires-Dist: pure-eval (==0.2.2)
Requires-Dist: pyparsing (==3.0.9)
Requires-Dist: python-dateutil (==2.8.2)
Requires-Dist: pyzmq (==25.1.1)
Requires-Dist: requests (==2.31.0)
Requires-Dist: six (==1.16.0)
Requires-Dist: stack-data (==0.6.2)
Requires-Dist: tornado (==6.3.3)
Requires-Dist: traitlets (==5.9.0)
Requires-Dist: urllib3 (==2.0.4)
Requires-Dist: wcwidth (==0.2.6)
